{
	"general": [
		{
			"question": "?לאיזו משפחה משתייכת הקינואה",
			"right_answer": 0,
			"answers": [
				"משפחת הסלקיים",
				"משפחת הדלועיים",
				"משפחת הדגניים",
				"משפחת הפירות"
			]
		},
		{
			"question": "?מהו צבע הפריחה של האורז",
			"right_answer": 2,
			"answers": [
				"אורז לא פורח",
				"צהוב",
				"ירוק",
				"לבן"
			]
		},
		{
			"question": "?מה הקשר בין מנדרינה לקלמנטינה",
			"right_answer": 0,
			"answers": [
				"קלמנטינה היא זן של מנדרינה",
				"מנדרינה היא זן של קלמנטינה",
				"המנדרינה היא הכלאה של קלמנטינה ותפוז",
				"שניהם בני דודים"
			]
		},
		{
			"question": ":בננה גדלה על",
			"right_answer": 1,
			"answers": [
				"גזע",
				"גזעול",
				"גבעול",
				"שיח"
			]
		},
		{
			"question": "?איזה מבין הזרעים הבאים משמש לייצור תחליף לקפה",
			"right_answer": 2,
			"answers": [
				"זרעי חמניה",
				"זרעי אבטיח",
				"זרעי במיה",
				"זרעי מלון"
			]
		},
		{
			"question": "?כיצד נוהג הפיל לישון",
			"right_answer": 1,
			"answers": [
				"בכריעה",
				"בעמידה",
				"בשכיבה על הצד",
				"פילים לא ישנים"
			]
		},
		{
			"question": "?נקבה של איזה בעל-חיים נוהגת לטרוף את הזכר בזמן ההזדווגות",
			"right_answer": 3,
			"answers": [
				"עקרב צהוב",
				"כלב ים",
				"למה",
				"גמל שלמה"
			]
		},
		{
			"question": "?מהי אורניתולוגיה",
			"right_answer": 2,
			"answers": [
				"אמנות ליטוש אבני חן",
				"תחום ברפואת שיניים",
				"ענף מחקר בזואולוגיה",
				"חקירת אבנים"
			]
		},
		{
			"question": "?מהי או מהו גמבוזיה",
			"right_answer": 0,
			"answers": [
				"מין דג טורף יתושים",
				"זן פלפל אדום גמדי",
				"חלודה בלטינית",
				"חלודה ביוונית"
			]
		},
		{
			"question": "?מהו מזונו העיקרי של הדוב הלבן",
			"right_answer": 1,
			"answers": [
				"צמחים ופירות",
				"כלבי ים",
				"דג נחש",
				"סלומון לבן"
			]
		},
		{
			"question": "?מאיזה מרחק מקסימלי מסוגל צבי להבחין בתנועה",
			"right_answer": 2,
			"answers": [
				"200 מטרים",
				"2000 מטרים",
				"1000 מטרים",
				"660 מטרים"
			]
		},
		{
			"question": "?הכלאה של אילו חיות הביאה ליצירת היעז",
			"right_answer": 2,
			"answers": [
				"יען ועז",
				"גנו ויעל",
				"יעל ועז",
				"יענה ועז"
			]
		},
		{
			"question": "?מתי התחיל השימוש בכרטיס האשראי המודרני",
			"right_answer": 1,
			"answers": [
				"בתחילת המאה ה-20",
				"בשנות ה-50 של המאה ה-20",
				"בסוף שנות ה-70 של המאה ה-20",
				"1981"
			]
		},
		{
			"question": "?היכן בגוף האדם נמצא איבר המכונה שבלול",
			"right_answer": 0,
			"answers": [
				"באוזן",
				"במערכת הלימפטית",
				"במעי הגס",
				"באף"
			]
		},
		{
			"question": "?מה משמעות השם בודהא",
			"right_answer": 2,
			"answers": [
				"מי שחולם",
				"מי שחוזה",
				"מי שהתעורר",
				"עצלן"
			]
		},
		{
			"question": "?מהו שמו העברי של הרָקוּן",
			"right_answer": 1,
			"answers": [
				"בואש",
				"דביבון רוחץ",
				"חולד",
				"עצלן"
			]
		},
		{
			"question": "?מהי החיה בעלת הקול החזק ביותר",
			"right_answer": 2,
			"answers": [
				"צרצר",
				"קוף",
				"לווייתן כחול",
				"אריה"
			]
		},
		{
			"question": "?מהי החיה הגדולה ביותר ביבשת צפון אמריקה",
			"right_answer": 1,
			"answers": [
				"אייל האלק",
				"דוב אפור",
				"ביזון",
				"דוב לבן"
			]
		},
		{
			"question": "?כיצד מתקשרת דבורת הדבש עם חברותיה לכוורת",
			"right_answer": 3,
			"answers": [
				"באמצעות זמזום",
				"באמצעות טביעת סימנים בדבש",
				"הן לא מתקשרות",
				"באמצעות ריקוד"
			]
		},
		{
			"question": "?עד לאיזה עומק מסוגל פינגווין לצלול",
			"right_answer": 2,
			"answers": [
				"10 מטרים",
				"20 מטרים",
				"200 מטרים",
				"500 מטרים"
			]
		},
		{
			"question": "?על פי הסברה המחקרית המקובלת, איזה יונק בויית לראשונה על ידי האדם",
			"right_answer": 3,
			"answers": [
				"חתול",
				"כבש",
				"שפן",
				"כלב"
			]
		},
		{
			"question": "?ממה בעיקר ניזונים דובי פנדה",
			"right_answer": 0,
			"answers": [
				"קנה במבוק",
				"נחשים",
				"פירות",
				"דגים"
			]
		},
		{
			"question": "?מהי אסטרטגיית ההגנה של השבלול",
			"right_answer": 1,
			"answers": [
				"קונכייה גדולה וחזקה",
				"התחפרות בקרקע",
				"הפרשת קצף רירי וארסי",
				"לברוח"
			]
		},
		{
			"question": "?באיזו יבשת לא ניתן למצוא ציפורי שיר",
			"right_answer": 2,
			"answers": [
				"אוסטרליה",
				"אסיה",
				"אנטארטיקה",
				"אירופה"
			]
		},
		{
			"question": "מהו המדבר הגדול ביותר בעולם",
			"right_answer": 1,
			"answers": [
				"מדבר גובי",
				"מדבר סהרה",
				"מדבר קלהארי",
				"מדבר סיני"
			]
		},
		{
			"question": "מהו החומר הטבעי הקשה ביותר בעולם",
			"right_answer": 3,
			"answers": [
				"טיטניום",
				"כספית",
				"אבנית",
				"יהלום"
			]
		},
		{
			"question": "לאיזה מהירות מגיע הצבי",
			"right_answer": 3,
			"answers": [
				"75",
				"120",
				"93",
				"80"
			]
		},
		{
			"question": "מהי בירת נורבגיה",
			"right_answer": 2,
			"answers": [
				"פריז",
				"ברלין",
				"אוסלו",
				"רומא"
			]
		},
		{
			"question": "?מדינה בעלת השטח הגדול ביותר",
			"right_answer": 1,
			"answers": [
				"ארצות הברית",
				"רוסיה",
				"קנדה",
				"אוסטרליה"
			]
		},
		{
			"question": "?מה המקום הגבוה ביותר בעולם",
			"right_answer": 3,
			"answers": [
				"ים המלח",
				"עמק הוואלי",
				"הרי האלפים",
				"האוורסט"
			]
		},
		{
			"question": "?מי צייר את מונה-ליזה",
			"right_answer": 3,
			"answers": [
				"דונאטלו",
				"רפאל",
				"מיכאלנגלו",
				"לאונרדו דה-וונצ'י."
			]
		},
		{
			"question": "?כמה זמן נמשכה מלחמת ששת הימים",
			"right_answer": 2,
			"answers": [
				"7 ימים",
				"8 ימים",
				"6 ימים",
				"56 ימים"
			]
		},
		{
			"question": "נשיא ארצות הברית",
			"right_answer": 0,
			"answers": [
				"דונאלד טראמפ",
				"רייגן",
				"ברק אובמה",
				"ביבי נתניהו"
			]
		},
		{
			"question": "?כמה צבעים יש לקשת",
			"right_answer": 1,
			"answers": [
				"3",
				"7",
				"9",
				"8"
			]
		},
		{
			"question": "? £ מה מסמל ",
			"right_answer": 3,
			"answers": [
				"ין",
				"אירו",
				"דולר",
				"פאונד"
			]
		},
		{
			"question": "?כמה צבי נינגה יש",
			"right_answer": 3,
			"answers": [
				"5",
				"3",
				"6",
				"4"
			]
		},
		{
			"question": "?כמה שניות יש בשעה",
			"right_answer": 0,
			"answers": [
				"3,600",
				"2,400",
				"3,864",
				"2,020"
			]
		},
		{
			"question": "'סה לה וי' באיטלקית",
			"right_answer": 2,
			"answers": [
				"להתראות",
				"בתאבון",
				"אלה החיים",
				"מה השעה?"
			]
		}
	],
	"history": [
		{
			"question": "?באיזה תאריך חל יום העצמאות האמריקאי",
			"right_answer": 1,
			"answers": [
				"2 באפריל",
				"4 ביולי",
				"1 בינואר",
				"1 באפריל"
			]
		},
		{
			"question": "?באיזו מדינה האוכלוסיה הכי גדולה כיום",
			"right_answer": 1,
			"answers": [
				"הודו",
				"סין",
				"יפן",
				"אוסטרליה"
			]
		},
		{
			"question": "?איזו חיה הייתה הראשונה לצאת לחלל",
			"right_answer": 1,
			"answers": [
				"קוף",
				"כלב",
				"חתול",
				"עכבר"
			]
		},
		{
			"question": "?בין מי למי נחתם החוזה השלום הראשון בהיסטוריה",
			"right_answer": 3,
			"answers": [
				"מלך יהודה ומלך מצרים",
				"מלך מצרים ומלך עמלק",
				"מלך ישראל ומלך יהודה",
				"מלך מצרים ומלך החתים"
			]
		},
		{
			"question": "?מהו שמו של כוכב הלכת הקרוב ביותר לכדור הארץ",
			"right_answer": 2,
			"answers": [
				"נפטון",
				"מאדים",
				"נגה",
				"ירח"
			]
		},
		{
			"question": "?מתי הוקמה מדינת ישראל",
			"right_answer": 1,
			"answers": [
				"1984",
				"1948",
				"1947",
				"1938"
			]
		},
		{
			"question": "?מתי ישו נולד",
			"right_answer": 1,
			"answers": [
				"990 לפני הספירה",
				"0 לספירה",
				"990 אחרי הספירה",
				"13 אחרי הספירה"
			]
		},
		{
			"question": "אברהם הוא אביו של : ",
			"right_answer": 1,
			"answers": [
				"יעקב",
				"יצחק",
				"משה",
				"יוסף"
			]
		},
		{
			"question": "?כמה מכות היכו במצרים",
			"right_answer": 3,
			"answers": [
				"11",
				"9",
				"8",
				"10"
			]
		},
		{
			"question": "?באיזה שנה התחילה מלחמת העולם הראשונה",
			"right_answer": 3,
			"answers": [
				"2020",
				"2048",
				"2036",
				"1914"
			]
		},
		{
			"question": "באיזה שנה הוקם צהל",
			"right_answer": 1,
			"answers": [
				"1984",
				"1948",
				"1947",
				"1938"
			]
		},
		{
			"question": "באיזה שנה הוקם פייסבוק",
			"right_answer": 1,
			"answers": [
				"2001",
				"2004",
				"1999",
				"2007"
			]
		},
		{
			"question": "מהו שמו האמצעי של מייקל ג'ורדן",
			"right_answer": 3,
			"answers": [
				"רון",
				"און",
				"דייויד",
				"ג'פרי"
			]
		},
		{
			"question": "היכן התקיים מונדיאל 1970",
			"right_answer": 3,
			"answers": [
				"רוסיה",
				"סין",
				"ברזיל",
				"מקסיקו"
			]
		}
	],
	"proggraming": [
		{
			"question": "PHP",
			"right_answer": 1,
			"answers": [
				"שפה בצד לקוח",
				"שפה בצד שרת",
				"מסד נתונים",
				"תוכנת עיצוב"
			]
		},
		{
			"question": "CSS",
			"right_answer": 3,
			"answers": [
				"Custom Style Sheets",
				"Custom Style Surfing",
				"Cascading System Sheets",
				"Cascading Style Sheets"
			]
		},
		{
			"question": "JavaScript Librarie: ",
			"right_answer": 1,
			"answers": [
				"CSS3",
				"jQuery",
				"Mongo",
				"WORDPRESS"
			]
		},
		{
			"question": "מקים חברת Apple",
			"right_answer": 3,
			"answers": [
				"קים ג'ונג און",
				"סטיב ווזניאק",
				"ביל גייטס",
				"סטיב ג'ובס"
			]
		},
		{
			"question": "true && false ?",
			"right_answer": 3,
			"answers": [
				"undefined",
				"true",
				"null",
				"false"
			]
		},
		{
			"question": "WWW",
			"right_answer": 0,
			"answers": [
				"World Wide Web",
				"World West Wine",
				"We Won Wimbeldon",
				"We Want Waffle"
			]
		},
		{
			"question": "true || true && false",
			"right_answer": 1,
			"answers": [
				"undefined",
				"true",
				"false",
				"null"
			]
		},
		{
			"question": "FTP",
			"right_answer": 0,
			"answers": [
				"פרוטוקול תקשורת להעברת קבצים",
				"ספרייה של ג'אווה סקריפט",
				"FINGER TYPE PRINT",
				"פרוטוקול תקשורת להעברת קבצי סאונד ווידאו"
			]
		},
		{
			"question": "מי ייסד את מייקרוסופט",
			"right_answer": 3,
			"answers": [
				"ביל גייטס",
				"סטיב ג'ובס",
				"גורג' סמית",
				"מנחם כהן"
			]
		},
		{
			"question": "1000 בבינארי",
			"right_answer": 1,
			"answers": [
				"6",
				"8",
				"8080",
				"1024"
			]
		},
		{
			"question": "console.log(1 + true);",
			"right_answer": 3,
			"answers": [
				"1",
				"undefined",
				"false",
				"2"
			]
		},
		{
			"question": "console.log(1 + '1');",
			"right_answer": 0,
			"answers": [
				"11",
				"2",
				"null",
				"undefined"
			]
		}
	]
}